golosscripts/__init__.py
golosscripts/bitshares_helper.py
golosscripts/decorators.py
golosscripts/feed.py
golosscripts/functions.py
golosscripts/golos_helper.py
golosscripts/monitor.py
golosscripts-1.0.0.dist-info/WHEEL
golosscripts-1.0.0.dist-info/METADATA
golosscripts-1.0.0.dist-info/RECORD
