Metadata-Version: 2.1
Name: golosscripts
Version: 1.0.0
Summary: Scripts for Golos blockchain
Home-page: https://github.com/bitfag/golos-scripts
License: MIT
Author: Vladimir Kamarzin
Author-email: vvk@vvk.pp.ru
Requires-Python: >=3.8,<4.0
Classifier: Development Status :: 3 - Alpha
Classifier: Intended Audience :: Developers
Classifier: License :: OSI Approved :: MIT License
Classifier: Operating System :: OS Independent
Classifier: Programming Language :: Python :: 3
Classifier: Programming Language :: Python :: 3.8
Classifier: Programming Language :: Python :: 3.9
Classifier: Topic :: Software Development :: Libraries :: Python Modules
Requires-Dist: bitshares (>=0.5.1,<0.6.0)
Requires-Dist: bitsharesscripts (>=2,<3)
Requires-Dist: ccxt (>=1.26.96,<2.0.0)
Requires-Dist: click (>=7.1.1,<8.0.0)
Requires-Dist: defusedxml (>=0.6.0,<0.7.0)
Requires-Dist: graphenelib (>=1.3.2,<2.0.0)
Requires-Dist: python-golos (>=1.1.0,<2.0.0)
Project-URL: Repository, https://github.com/bitfag/golos-scripts
